[{"id": 450330966, "text": "$btai $negg $bbai $msft $wmt  \n$1800 into $54k in the last 30 days. If you really want to make huge profits on trading then, Join this winning chat: \n   bit.ly/3IYt8Cg", "time": 1649283397.0, "sentiment": ""}, {"id": 450330552, "text": "Still not bottom today, more lows for these \n  $TSLA 1027.9  $MSFT 297.21  $GOOGL 2725.64", "time": 1649283331.0, "sentiment": ""}, {"id": 450330502, "text": "$MSFT our 2nd biggest mkt cap down more than chinese stocks $AAPL $SPY \ud83d\ude02\ud83d\ude02\ud83d\ude02\ud83d\udd2b", "time": 1649283323.0, "sentiment": ""}, {"id": 450330257, "text": "$MSFT IS A TRUE CHAMP", "time": 1649283286.0, "sentiment": ""}, {"id": 450330135, "text": "$MSFT i wish i had anything else to throw at this right now", "time": 1649283267.0, "sentiment": ""}, {"id": 450329993, "text": "$MSFT BY 2PM  AFTER THE BS----UP", "time": 1649283245.0, "sentiment": ""}, {"id": 450329716, "text": "$MSFT A megacap down 4%+ is unheard of\u2026 might have to buy\u2026", "time": 1649283199.0, "sentiment": ""}, {"id": 450329624, "text": "$MSFT literally everything else holding steady \ud83d\ude02\ud83d\ude02\ud83d\ude02\ud83d\ude02\ud83d\ude02\ud83d\ude02\ud83d\ude02\ud83d\ude02\ud83d\ude02 omfg", "time": 1649283186.0, "sentiment": ""}, {"id": 450329038, "text": "$MSFT Even big tech software getting killed.", "time": 1649283098.0, "sentiment": ""}, {"id": 450328965, "text": "$MSFT is there a gap that needs to be filled? Lol..", "time": 1649283089.0, "sentiment": ""}, {"id": 450328840, "text": "$MSFT 275", "time": 1649283071.0, "sentiment": ""}, {"id": 450328750, "text": "$SPY what an opportunity for bulls to buy cheap stocks $MSFT $AAPL $TSLA", "time": 1649283055.0, "sentiment": "Bearish"}, {"id": 450328740, "text": "$MSFT 315 lotto call", "time": 1649283054.0, "sentiment": ""}, {"id": 450328665, "text": "$MSFT RECESSION OR NOT! UP ON GOOD EARNINGS SOON", "time": 1649283042.0, "sentiment": ""}, {"id": 450328634, "text": "$MSFT Buy it alllllll the way down", "time": 1649283037.0, "sentiment": "Bullish"}, {"id": 450328585, "text": "$MSFT give up bulls. Live to fight another day lol", "time": 1649283027.0, "sentiment": ""}, {"id": 450328148, "text": "$MSFT down 4% \ud83d\ude04", "time": 1649282952.0, "sentiment": ""}, {"id": 450328088, "text": "$MSFT this will recover so fast", "time": 1649282942.0, "sentiment": ""}, {"id": 450328036, "text": "$MSFT is brandon speaking?", "time": 1649282935.0, "sentiment": ""}, {"id": 450327961, "text": "$MSFT over done. back to 305 at 2pm est.  fed will back off", "time": 1649282924.0, "sentiment": "Bullish"}, {"id": 450327029, "text": "$qqq $msft $aapl https://www.youtube.com/watch?v=H0V6_VgPUjU", "time": 1649282765.0, "sentiment": ""}, {"id": 450327023, "text": "$MSFT This is &quot;Clearly&quot; a coordinated attack on MSFT today.. I wouldnt sell anything or panic... See&#39;s 300&#39;s before the days out!", "time": 1649282764.0, "sentiment": "Bullish"}, {"id": 450326631, "text": "$MSFT still holding these calls, whos ready for me to sell for this to take off?", "time": 1649282702.0, "sentiment": ""}, {"id": 450326418, "text": "$MSFT \nare they buying somebody \ud83e\udd2d", "time": 1649282671.0, "sentiment": "Bullish"}, {"id": 450326360, "text": "$MSFT mother of god what\u2019s happening folks", "time": 1649282662.0, "sentiment": ""}, {"id": 450326006, "text": "$MSFT my god", "time": 1649282597.0, "sentiment": ""}, {"id": 450325951, "text": "$MSFT mobq small cap", "time": 1649282589.0, "sentiment": "Bullish"}, {"id": 450325834, "text": "$MSFT In the recent reporting quarter: 0 institutions initiated a position, while 0 completely liquidated https://www.insider-analysis.com/search_whales.php?ticker=TABLE_MSFT", "time": 1649282571.0, "sentiment": ""}, {"id": 450325455, "text": "$MSFT Straight up massacre", "time": 1649282509.0, "sentiment": "Bearish"}, {"id": 450325092, "text": "$MSFT what the world going on \ud83c\udf0e", "time": 1649282457.0, "sentiment": "Bullish"}]