[{"id": 454939045, "text": "$spy wow $msft missed on eps", "time": 1651021688.0, "sentiment": ""}, {"id": 454939035, "text": "$MSFT Both this and Google f---ed.", "time": 1651021686.0, "sentiment": ""}, {"id": 454939030, "text": "$MSFT bears excited to see the markers and economy fall? weird", "time": 1651021686.0, "sentiment": ""}, {"id": 454939015, "text": "$MSFT fucccckkkkkkk", "time": 1651021684.0, "sentiment": ""}, {"id": 454938979, "text": "$MSFT im sorry did they miss or something..?", "time": 1651021681.0, "sentiment": ""}, {"id": 454938970, "text": "$MSFT Wow ! I\u2019m surprised honestly", "time": 1651021680.0, "sentiment": "Bearish"}, {"id": 454938946, "text": "$MSFT  &quot;Microsoft reported quarterly earnings of $2.22 per share which beat the analyst consensus estimate of $2.18 by 1.83 percent. This is a 13.85 percent increase over earnings of $1.95 per share from the same period last year.&quot;", "time": 1651021676.0, "sentiment": "Bullish"}, {"id": 454938925, "text": "$SPY the fear is now extreme. The sell off is over $GOOG $MSFT", "time": 1651021674.0, "sentiment": ""}, {"id": 454938903, "text": "$MSFT ", "time": 1651021672.0, "sentiment": "Bearish"}, {"id": 454938897, "text": "$MSFT $AMZN $AAPL $googl $tsla\nNext is Amazon and Apple.", "time": 1651021671.0, "sentiment": "Bearish"}, {"id": 454938876, "text": "$GOOGL $MSFT Initial response, not favorable", "time": 1651021669.0, "sentiment": "Bearish"}, {"id": 454938862, "text": "@StockBookie Especially $MSFT  \ud83d\ude2c", "time": 1651021668.0, "sentiment": ""}, {"id": 454938861, "text": "$MSFT did they miss too?", "time": 1651021667.0, "sentiment": ""}, {"id": 454938839, "text": "$MSFT dam ripp my calls", "time": 1651021665.0, "sentiment": ""}, {"id": 454938825, "text": "$SPY $GOOGL $MSFT  $GM \n\ud83e\ude78\ud83e\ude78\ud83e\ude78\ud83e\ude78\ud83e\ude78\ud83e\ude78\ud83e\ude78\ud83e\ude78\ud83e\ude78", "time": 1651021664.0, "sentiment": ""}, {"id": 454938795, "text": "$MSFT rip market tomorrow", "time": 1651021662.0, "sentiment": "Bearish"}, {"id": 454938785, "text": "$NVDA $AMD Wow selling off on those $GOOGL $MSFT earnings...", "time": 1651021660.0, "sentiment": ""}, {"id": 454938754, "text": "$MSFT can this save the market?", "time": 1651021657.0, "sentiment": ""}, {"id": 454938725, "text": "$MSFT wow it\u2019s tanking", "time": 1651021654.0, "sentiment": "Bullish"}, {"id": 454938671, "text": "$MSFT The Eve of a long bear market, the deterioration has begun", "time": 1651021648.0, "sentiment": "Bearish"}, {"id": 454938662, "text": "$PLTR \n$MSFT $GOOG both got doomed\u2026\nNow get ready for $AMD disaster and followed by $PLTR", "time": 1651021646.0, "sentiment": "Bearish"}, {"id": 454938652, "text": "$MSFT bloodbath \ud83e\ude78", "time": 1651021645.0, "sentiment": ""}, {"id": 454938637, "text": "$MSFT Earnings: $2.22 per share, adjusted, vs. $2.19 as expected by analysts, according to Refinitiv. \nRevenue: $49.36 billion, vs. $49.05 billion as expected by analysts, according to Refinitiv.", "time": 1651021643.0, "sentiment": ""}, {"id": 454938627, "text": "$MSFT waiting for 200 let&#39;s seee", "time": 1651021643.0, "sentiment": "Bearish"}, {"id": 454938613, "text": "$MSFT &amp; $GOOGL \ud83e\udd74\ud83e\udd76", "time": 1651021641.0, "sentiment": ""}, {"id": 454938584, "text": "$MSFT going up after cc", "time": 1651021638.0, "sentiment": ""}, {"id": 454938550, "text": "$MSFT it&#39;s a BEAT.  Bears, you know it&#39;ll go up and down for some minutes, and then move up, naturally.  You had your time.  Now...", "time": 1651021634.0, "sentiment": "Bullish"}, {"id": 454938541, "text": "$aapl $msft $goog $tsla\n\nHide yo kids hide yo wife\n\n\ud83e\ude78 \ud83d\udd2a", "time": 1651021633.0, "sentiment": ""}, {"id": 454938539, "text": "$AAPL $GOOG crashing and $MSFT not looking strong, shows where Apple will be heading", "time": 1651021633.0, "sentiment": "Bearish"}, {"id": 454938513, "text": "$MSFT BEAT! Sells off.....", "time": 1651021630.0, "sentiment": ""}]