[{"id": 454984748, "text": "$MSFT REVENUE GROWTH, RECORDS, GROWTH, WITH FKING SHUTDOWNS, BEARS TOMORROW MOASSSSSSS", "time": 1651028854.0, "sentiment": "Bullish"}, {"id": 454984747, "text": "$MSFT wow. Wtf. Let\u2019s fuckinh goooo", "time": 1651028854.0, "sentiment": "Bullish"}, {"id": 454984745, "text": "$MSFT let\u2019s do $300\ud83e\udd11\ud83e\udd11\ud83d\ude80", "time": 1651028853.0, "sentiment": ""}, {"id": 454984731, "text": "$MSFT current state of MSFT", "time": 1651028850.0, "sentiment": "Bullish"}, {"id": 454984728, "text": "$MSFT now that\u2019s better", "time": 1651028849.0, "sentiment": "Bullish"}, {"id": 454984723, "text": "$SPY Wow $MSFT", "time": 1651028847.0, "sentiment": "Bullish"}, {"id": 454984721, "text": "$MSFT kek", "time": 1651028847.0, "sentiment": ""}, {"id": 454984695, "text": "$MSFT Conference Call:\n\n- Azure revenue ahead of expectations. \n- Azure $100M deals doubled YoY. \n- LinkedIn 830M Professionals use this platform\n- Outlook: Intelligent Cloud Revenue - $21.1B to 21.35B \n\nStock turned green in AH.", "time": 1651028841.0, "sentiment": "Bullish"}, {"id": 454984684, "text": "$MSFT Let&#39;s gooo boooooys!", "time": 1651028840.0, "sentiment": "Bullish"}, {"id": 454984681, "text": "$MSFT wow up 18$ now wholly craap", "time": 1651028838.0, "sentiment": ""}, {"id": 454984670, "text": "$MSFT good numbers", "time": 1651028836.0, "sentiment": ""}, {"id": 454984668, "text": "Moving $MSFT", "time": 1651028836.0, "sentiment": ""}, {"id": 454984659, "text": "$MSFT dopee", "time": 1651028834.0, "sentiment": "Bullish"}, {"id": 454984656, "text": "$MSFT \ud83d\ude35\u200d\ud83d\udcab", "time": 1651028833.0, "sentiment": ""}, {"id": 454984648, "text": "$MSFT what just happened here", "time": 1651028831.0, "sentiment": ""}, {"id": 454984644, "text": "$MSFT to 400 we go...", "time": 1651028830.0, "sentiment": "Bullish"}, {"id": 454984615, "text": "$MSFT ABOVE 200 MA $300+ LOVE THIS LADY WHO&#39;S TALKING", "time": 1651028823.0, "sentiment": "Bullish"}, {"id": 454984602, "text": "$MSFT crazy", "time": 1651028821.0, "sentiment": "Bullish"}, {"id": 454984590, "text": "$MSFT look for the gap and crap tomorrow", "time": 1651028818.0, "sentiment": ""}, {"id": 454984586, "text": "$MSFT oh man straight up\ud83e\udd11\ud83e\udd11\ud83d\ude80", "time": 1651028817.0, "sentiment": ""}, {"id": 454984576, "text": "$MSFT $300 tomorrow huge spike just now", "time": 1651028815.0, "sentiment": "Bullish"}, {"id": 454984566, "text": "Nice move on guidance $MSFT", "time": 1651028814.0, "sentiment": ""}, {"id": 454984562, "text": "@DefinitelyNotShortSeller Watch $MSFT rip pre market tomorrow and crowd jumping in (hopefully lol). sentiments are extremely low, and that\u2019s when big money could flow in for quick trades. Look at tech and bio $LABU, down the drain. This is low risk high reward trades compared to playing ers for specific companies IMO.", "time": 1651028814.0, "sentiment": ""}, {"id": 454984550, "text": "$MSFT I TOLD YOU, THIS SHIT IS SO FKING BULLISH THIS SHOULD BE 350$, MOST FKING BULLISH CALL I HAVE BEEN ON", "time": 1651028811.0, "sentiment": "Bullish"}, {"id": 454984540, "text": "$MSFT based on their estimates their revenue going to shoot up at least 27 percent are they for real? this is going to rocket", "time": 1651028809.0, "sentiment": ""}, {"id": 454984539, "text": "$MSFT congrats longs! \ud83d\ude80", "time": 1651028808.0, "sentiment": ""}, {"id": 454984533, "text": "$MSFT don\u2019t bet against Bill", "time": 1651028807.0, "sentiment": "Bullish"}, {"id": 454984527, "text": "$MSFT HAHA!!!!!", "time": 1651028806.0, "sentiment": "Bullish"}, {"id": 454984521, "text": "$MSFT $300 tm", "time": 1651028803.0, "sentiment": "Bullish"}, {"id": 454984517, "text": "$MSFT There comes 290 baby...expecting close to 300 tonight", "time": 1651028802.0, "sentiment": "Bullish"}]