[{"id": 454995943, "text": "$MSFT I know all puts are worthless right now \ud83d\ude02", "time": 1651031651.0, "sentiment": ""}, {"id": 454995898, "text": "$SPY at least if we get analyst downgrades in $MSFT and $GOOGL we can have someone bearish to turn more bullish", "time": 1651031640.0, "sentiment": ""}, {"id": 454995890, "text": "$MSFT hold this level we bull tom", "time": 1651031637.0, "sentiment": ""}, {"id": 454995777, "text": "$MSFT \ud83d\udd25\ud83d\ude80 Microsoft calls", "time": 1651031607.0, "sentiment": "Bullish"}, {"id": 454995754, "text": "$SPY never thought my $MSFT 290$ could be in the money tomorrow \ud83e\udd37\u200d\u2642\ufe0f", "time": 1651031601.0, "sentiment": ""}, {"id": 454995681, "text": "$MSFT beware of institutional selling into retail buying tomorrow.", "time": 1651031580.0, "sentiment": "Bearish"}, {"id": 454995674, "text": "$MSFT This is nothing. Just wait and see what it does when the market goes green.", "time": 1651031578.0, "sentiment": "Bullish"}, {"id": 454995633, "text": "$MSFT  22-1 sells to buys", "time": 1651031566.0, "sentiment": ""}, {"id": 454995626, "text": "$MSFT vs shorts", "time": 1651031565.0, "sentiment": "Bullish"}, {"id": 454995486, "text": "$MSFT  will it hold green at the close of After Hours???", "time": 1651031521.0, "sentiment": ""}, {"id": 454995416, "text": "$MSFT", "time": 1651031499.0, "sentiment": "Bullish"}, {"id": 454995387, "text": "$MSFT THE PUMP BEGINS", "time": 1651031490.0, "sentiment": "Bullish"}, {"id": 454995332, "text": "$SPY bulls are excited because it\u2019s the only hope they have left before bankruptcy! $MSFT", "time": 1651031473.0, "sentiment": ""}, {"id": 454995254, "text": "$MSFT lolll, keep buying the fake pump by the algos and the tutes!!!!\ud83d\udc4d\ud83d\udc4d\ud83d\udc4d\ud83d\udc4d\n\nBloody waterfall at open is 100% guaranteed!\n\nMark this post \ud83d\udc4d\ud83d\udc4d\ud83d\udc4d\ud83e\ude78\ud83e\ude78\ud83e\ude78\ud83e\ude78", "time": 1651031451.0, "sentiment": "Bearish"}, {"id": 454995247, "text": "$MSFT we good!", "time": 1651031449.0, "sentiment": "Bullish"}, {"id": 454995239, "text": "$MSFT Uh oh!!!!  Did the bears go into hibernation???", "time": 1651031447.0, "sentiment": "Bullish"}, {"id": 454995222, "text": "$MSFT its going to go parabolic, has to", "time": 1651031444.0, "sentiment": "Bullish"}, {"id": 454995221, "text": "$MSFT I cuss a little .. WTF why is down again .. \ud83d\udd7a wtff", "time": 1651031444.0, "sentiment": "Bullish"}, {"id": 454995206, "text": "$MSFT anything on the call about completion of $ATVI buyout?", "time": 1651031441.0, "sentiment": ""}, {"id": 454995177, "text": "$MSFT If we get above 290 region, there will be gravitational pull towards 300. May happen in the morning.", "time": 1651031435.0, "sentiment": "Bullish"}, {"id": 454995089, "text": "$MSFT lets go baby. Whoop \ud83d\ude4c\ud83c\udfff", "time": 1651031412.0, "sentiment": ""}, {"id": 454995043, "text": "$MSFT Evidently Microsoft had a killer conference call \u260e\ufe0f that\u2019s a wrap bears \ud83d\udc3b", "time": 1651031398.0, "sentiment": "Bullish"}, {"id": 454994922, "text": "Most Mentioned Tickers on WSB \n \n1. $TSLA \n2. $MSFT \n3. $FB \n4. $GOOGL", "time": 1651031360.0, "sentiment": ""}, {"id": 454994842, "text": "$MSFT this is the Noah to lead the rest of stock market to safety", "time": 1651031338.0, "sentiment": "Bullish"}, {"id": 454994685, "text": "$MSFT It\u2019s already heading down from profit takers and - After shorts exit it will only be up 2- 3% for one day then back down it goes\u2026.. Happens every time\u2026", "time": 1651031291.0, "sentiment": ""}, {"id": 454994669, "text": "$AAPL $MSFT Just posting this $TSLA chart for any fools who get excited on an earnings bounce. This is what happens in bear markets", "time": 1651031287.0, "sentiment": "Bearish"}, {"id": 454994635, "text": "$MSFT thank you for saving the markets tonight and tomorrow!!", "time": 1651031278.0, "sentiment": "Bullish"}, {"id": 454994620, "text": "$MSFT are 290c alive..\ud83e\udd14", "time": 1651031273.0, "sentiment": ""}, {"id": 454994589, "text": "$MSFT good comeback", "time": 1651031264.0, "sentiment": "Bullish"}, {"id": 454994564, "text": "$SPY maybe Bill Gates isn\u2019t evil after all $MSFT", "time": 1651031259.0, "sentiment": ""}]