[{"id": 454844412, "text": "$AAPL this is honestly the safest place to park your money during this scary ass stock/crypto market. LIKE IF YOU AGREE\ud83d\udc4d\ud83c\udffb", "time": 1651007071.0, "sentiment": "Bullish"}, {"id": 454844242, "text": "$QQQ $MSFT $AAPL  measured leg down if msft and aapl misses earnings this week", "time": 1651007045.0, "sentiment": "Bearish"}, {"id": 454843823, "text": "$QQQ what happens tomorrow if $AAPL $GOOG $MSFT all miss earnings?", "time": 1651006986.0, "sentiment": ""}, {"id": 454843463, "text": "$AAPL anyone trying to play apex while our puts print today?", "time": 1651006935.0, "sentiment": ""}, {"id": 454843431, "text": "$BKKT $AAPL Marriott and Wyndham are just the beginning once you&#39;re in with Apple and Google pay.", "time": 1651006931.0, "sentiment": "Bullish"}, {"id": 454843330, "text": "@MSX2022 What happens tomorrow if $AAPL $GOOG  $MSFT miss earnings?", "time": 1651006919.0, "sentiment": ""}, {"id": 454843199, "text": "$AAPL 130 for this Chinese company", "time": 1651006903.0, "sentiment": "Bearish"}, {"id": 454843145, "text": "Sweep Options Activity: $AAPL is the #1 ticker with sweep activity where institutions are trading options urgently with 27.4K sweep contracts, a leading indicator of market movement.\n\nMarket analysis and options contracts included in screenshot of dashboard from \ud83d\udd25 INSIDERFINANCE.IO \ud83d\udd25 (Link in profile - @InsiderFinance)", "time": 1651006896.0, "sentiment": ""}, {"id": 454843032, "text": "$AAPL Sentiment Alert: $AAPL Increasing bearish pressure with an imbalance in net option delta of -1.8 M. https://tinyurl.com/y686h8pj", "time": 1651006883.0, "sentiment": ""}, {"id": 454842692, "text": "$AAPL  \n \nwhere do we stick the fork?", "time": 1651006838.0, "sentiment": ""}, {"id": 454842621, "text": "$AAPL \u2026buy it", "time": 1651006828.0, "sentiment": ""}, {"id": 454842491, "text": "$QQQ $SPY $TSLA $AAPL I called it last night, most of you didn\u2019t listen \ud83e\udd26\ud83c\udffd\u200d\u2642\ufe0f limit down tomorrow when all ER come out bad", "time": 1651006813.0, "sentiment": "Bearish"}, {"id": 454842448, "text": "$SPY damn trimmed my $AAPL puts too soon", "time": 1651006807.0, "sentiment": ""}, {"id": 454842004, "text": "$AAPL funny how all of a sudden China can\u2019t get their shit together on covid. Makes you wonder.", "time": 1651006747.0, "sentiment": ""}, {"id": 454841945, "text": "$AAPL worked fine.", "time": 1651006740.0, "sentiment": ""}, {"id": 454841906, "text": "$AAPL this is beautiful. Hopefully goes sub $100. Of course I\u2019m bullish long term but it\u2019s so overpriced it\u2019s not funny. Gained 2 trillion in market cap over 2 years without significant changes. How is that justified?", "time": 1651006735.0, "sentiment": ""}, {"id": 454841688, "text": "$SPY $AMD $NVDA $QQQ $AAPL serious survey- for those that voted for Biden, how is your life better today than is was under Trump?", "time": 1651006708.0, "sentiment": ""}, {"id": 454841419, "text": "$SPY $AAPL $MSFT Apple \ud83c\udf4e below $140 SPY below \u2b07\ufe0f $400 and MSFT below $250", "time": 1651006670.0, "sentiment": "Bearish"}, {"id": 454841281, "text": "@MarketAce shorting $aapl target $.70 $evok  \n \n\ud83e\udd21", "time": 1651006650.0, "sentiment": ""}, {"id": 454841101, "text": "$AAPL $TSLA $QQQ tech liquidated", "time": 1651006625.0, "sentiment": ""}, {"id": 454840756, "text": "$AAPL here we are again at 200 day", "time": 1651006576.0, "sentiment": ""}, {"id": 454840640, "text": "$SPX $TSLA $AAPL $CRM - short at SQQQ \ud83e\udd26\u200d\u2642\ufe0f", "time": 1651006559.0, "sentiment": ""}, {"id": 454840376, "text": "$NFLX $AAPL $TSLA $GOOGL $NVDA \nFolks cancelled Even $10 Netflix subscriptions. \nThey won&#39;t buy $1000 new iPhones", "time": 1651006521.0, "sentiment": "Bearish"}, {"id": 454840347, "text": "$SPY  \n \n$TSLA - 800 \n$AAPL - 150 \nVIX  - 37.50 \nUVXY - 21 \n \nhttps://twitter.com/MeisaBonelli/status/1518981403538505730?s=20&amp;t=OpESZ1XWfNS-xehqm7_ncA \n \n$QQQ $IWM", "time": 1651006515.0, "sentiment": ""}, {"id": 454839709, "text": "$AAPL should change the name to Lemon", "time": 1651006422.0, "sentiment": ""}, {"id": 454839494, "text": "Unusual Options Activity: $AAPL is the #26 ticker with unusual activity from institutional traders with an average of 10% out of the money, a leading indicator of market movement.\n\nMarket analysis and options contracts included in screenshot of dashboard from \ud83d\udd25 INSIDERFINANCE.IO \ud83d\udd25 (Link in profile - @InsiderFinance)", "time": 1651006392.0, "sentiment": ""}, {"id": 454839480, "text": "$SPY $AAPL $MSFT $TSLA $NVDA \nNo ones will buy iPhone, EV, Computer chip in the middle of recession\n\nhttps://www.google.com/amp/s/www.forbes.com/sites/simonconstable/2022/04/26/europe-faces-higher-recession-risks--than-usa/amp/", "time": 1651006390.0, "sentiment": "Bearish"}, {"id": 454839217, "text": "$AAPL time for a ramp \ud83e\udd11\ud83e\udd11\ud83d\ude80\ud83d\ude80", "time": 1651006349.0, "sentiment": ""}, {"id": 454839131, "text": "$AAPL $spy $ndx $amzn short at $sqqq - markets returning to Feb 2020", "time": 1651006338.0, "sentiment": ""}, {"id": 454838591, "text": "$AAPL  BRANDON  explaining current events.......", "time": 1651006256.0, "sentiment": ""}]