[{"id": 453722300, "text": "$NVDA 230 today?", "time": 1650566416.0, "sentiment": "Bullish"}, {"id": 453722280, "text": "$NVDA Shorted above 223 again \ud83d\ude02\nWorks every single time", "time": 1650566413.0, "sentiment": "Bearish"}, {"id": 453722099, "text": "$NVDA shorted", "time": 1650566388.0, "sentiment": "Bearish"}, {"id": 453721709, "text": "$NVDA  Looking for a reason for the run-up? Could be $LRCX ER beat IMO. May now see some profit taking.  Am thinking sideways for a few hours.", "time": 1650566340.0, "sentiment": ""}, {"id": 453721650, "text": "$NVDA \n\nBlatant sell off coming?", "time": 1650566332.0, "sentiment": "Bullish"}, {"id": 453721132, "text": "$AMD $NVDA already up 4% (basically back to yesterday open) and we&#39;re struggling at 96? WTF", "time": 1650566263.0, "sentiment": ""}, {"id": 453721101, "text": "$NVDA RUNNER", "time": 1650566260.0, "sentiment": "Bullish"}, {"id": 453720863, "text": "$NVDA monster green dick", "time": 1650566229.0, "sentiment": "Bullish"}, {"id": 453720805, "text": "$NVDA above 225, big run up gonna happen", "time": 1650566219.0, "sentiment": ""}, {"id": 453720718, "text": "$NVDA out my overnight calls \u2014 thanks all", "time": 1650566206.0, "sentiment": "Bullish"}, {"id": 453720686, "text": "These are my top four gainers this morning: $BKKT $BX $GBTC $NVDA\n\nLet\u2019s go!!!", "time": 1650566203.0, "sentiment": "Bullish"}, {"id": 453720550, "text": "$NVDA Bam! I didn&#39;t even hear the bell before it took off", "time": 1650566186.0, "sentiment": "Bullish"}, {"id": 453720461, "text": "$NVDA this thing bounces up quick very liquid stock", "time": 1650566172.0, "sentiment": ""}, {"id": 453720403, "text": "$NVDA lets go baby", "time": 1650566165.0, "sentiment": "Bullish"}, {"id": 453720256, "text": "$NVDA jesus!", "time": 1650566141.0, "sentiment": "Bullish"}, {"id": 453720001, "text": "$NVDA \ud83d\ude2c\ud83d\ude2c", "time": 1650566106.0, "sentiment": "Bearish"}, {"id": 453719875, "text": "$NVDA earnings are on May 25th correct?", "time": 1650566089.0, "sentiment": ""}, {"id": 453719658, "text": "$NVDA lets test 226 for the 5th time.", "time": 1650566061.0, "sentiment": "Bullish"}, {"id": 453719544, "text": "$NVDA even though it\u2019s a bear market, the fair value of this company should be at least 300", "time": 1650566042.0, "sentiment": "Bullish"}, {"id": 453719488, "text": "$NVDA wus the matter bears, you ain&#39;t no red here today", "time": 1650566034.0, "sentiment": "Bullish"}, {"id": 453719041, "text": "$NVDA \ud83c\udd99\ud83d\ude80\ud83d\ude80", "time": 1650565969.0, "sentiment": "Bullish"}, {"id": 453718667, "text": "$NVDA gonna dump to 212 by 11:30", "time": 1650565915.0, "sentiment": "Bearish"}, {"id": 453718556, "text": "$NVDA and now they dump that\u2019s the high for the day", "time": 1650565894.0, "sentiment": ""}, {"id": 453718418, "text": "Thinking about trading options or stock in Tesla, Marriott, Alaska Air, NVIDIA, or Royal Caribbean Cruises?  $ALK $MAR $NVDA $RCL $TSLA \n\nhttps://newsfilter.io/a/4b4f74d76a74ee2aae933f8b121289ce", "time": 1650565868.0, "sentiment": ""}, {"id": 453717785, "text": "$NVDA", "time": 1650565758.0, "sentiment": "Bullish"}, {"id": 453717758, "text": "$NVDA watching for 216.3 218,219+", "time": 1650565753.0, "sentiment": ""}, {"id": 453717675, "text": "Won&#39;t look to trade these stocks until they&#39;re out of these zones... \n \n$AMZN  \nUpside: 3175 \nDownside: 3000 \n \n$NVDA  \nUpside: 228 \nDownside: 210-208 \n \n$GOOGL  \nUpside: 2620 \nDownside: 2520 \n \nFOLLOW \n&amp; LETS MAKE MONEY\ud83d\udcb0 \n$SPY $QQQ", "time": 1650565740.0, "sentiment": "Bullish"}, {"id": 453717538, "text": "Favs: $UAL over 50.80, $BA over 188, $NVDA over 219, $AA under 79.50!", "time": 1650565718.0, "sentiment": ""}, {"id": 453717463, "text": "$NVDA puts below 216.50 break", "time": 1650565706.0, "sentiment": "Bearish"}, {"id": 453716642, "text": "\ud83d\udd2eBest Large Cap Parabolics from 2021:  \nCalled $TSLA on 6/17/2019 at 44.81 --&gt; 1,203.23 Returns +2,585.18% \nCalled $AMD on 3/28/2019 at 25.13 --&gt; 162.07 Returns +545.05% \nCalled $SQ on 8/18/2019 at 62.96 --&gt; 275.77 Return +338.01% \nCalled $NVDA on 11/9/2019 at 207.85 --&gt; 801.50 Returns +285.61% \nCalled $AAPL on 5/14/2019 at 47.24 --&gt; 153.58 Returns +225.12%", "time": 1650565560.0, "sentiment": "Bullish"}]