[{"id": 437175524, "text": "$CSCO NEW ARTICLE : Cisco announces $15 billion stock buyback program, DoorDash shares soar on Q4 sales https://www.stck.pro/news/CSCO/23055381", "time": 1645134404.0, "sentiment": ""}, {"id": 437173607, "text": "Cisco Systems&#39;s PT raised by Cowen Inc to $66.00. https://www.marketbeat.com/r/1715371 $CSCO", "time": 1645134152.0, "sentiment": ""}, {"id": 437172904, "text": "Most gaining stocks in the S&amp;P500 today: $CSCO, $DLR and $AIG https://www.chartmill.com/stock/stock-screener?v=3&amp;f=ind_22&amp;s=pt&amp;utm_source=stocktwits&amp;utm_medium=screener&amp;utm_content=Stock_Screener:_top_S&amp;P500_gainers&amp;utm_campaign=social_tracking", "time": 1645134060.0, "sentiment": ""}, {"id": 437171114, "text": "Peak profit for the last 6 expired option alerts for $CSCO 309.62| 7.27| 161.22| 41.67| 280.85| 171.19|", "time": 1645133817.0, "sentiment": ""}, {"id": 437169607, "text": "$CSCO This one is worth watching for possible day trade on call options", "time": 1645133614.0, "sentiment": ""}, {"id": 437168938, "text": "Can The 200-Day Moving Average Hold Under Rising Russian Tension And Negative Economic News?  $WMT $NVDA $AMT $CSCO $SPLK \n\nhttps://newsfilter.io/a/a0e7e3c00a22daa45764a7036df35862", "time": 1645133526.0, "sentiment": ""}, {"id": 437168022, "text": "$CSCO \n\nStrong as rock in this stupid market! When calm returns to the market, this will rocket into the $60\u2019s! \n\ud83d\udd25\ud83d\udd25\ud83d\udd25\ud83d\ude80\ud83d\ude80\ud83d\ude80", "time": 1645133412.0, "sentiment": "Bullish"}, {"id": 437164400, "text": "$CSCO awesome news, company announces 15 billion buy back program. And easy ride back over 60 bucks.", "time": 1645132958.0, "sentiment": "Bullish"}, {"id": 437159814, "text": "$CSCO \ud83d\udce1 Cowen &amp; Co. reiterated coverage on Cisco Systems with a new price target\n\nhttps://quantisnow.com/insight/2434491?s=s\n\nThis and other insights appear 45 seconds early at \ud83d\udcaa https://quantisnow.com/feed \ud83d\udcaa", "time": 1645132359.0, "sentiment": ""}, {"id": 437159458, "text": "$CSCO Cowen &amp; Co. analyst Paul Silverstein maintains Cisco Systems with a Outperform and raises the price target from $61 to $66.", "time": 1645132316.0, "sentiment": ""}, {"id": 437155609, "text": "Top Implied #Volatility Decliners $PLTR $CSCO $DASH https://tinyurl.com/y2x6mugt", "time": 1645131827.0, "sentiment": ""}, {"id": 437153545, "text": "$CSCO just crossed above its 20-day moving average.\n\nChart: https://marketcharts.com/page/a22d93eb", "time": 1645131576.0, "sentiment": ""}, {"id": 437153321, "text": "$CSCO bounces back with nice quarter after rare top line miss last time  https://www.briefing.com/in-depth-analysis/Content/Article?ArticleId=IN20220217095334CSCO", "time": 1645131549.0, "sentiment": ""}, {"id": 437149417, "text": "$IRNT just so $CSCO on CNBC saying that they will do more on cybersecurity in the next 12 months !!!!!! another potential buyer looking for us \u2026\u2026.", "time": 1645131074.0, "sentiment": "Bullish"}, {"id": 437148458, "text": "$CSCO Nice quarter, the CEO forgot to thank the most instrumental figure in providing such, Powell lol", "time": 1645130952.0, "sentiment": "Bearish"}, {"id": 437147954, "text": "$CSCO looki ng for a push back above the 10ema", "time": 1645130889.0, "sentiment": "Bullish"}, {"id": 437146565, "text": "$CSCO good earnings nice chart - buy signals 5/30/60/ daily - still early but - IV back to 30% HV 28% #BLOG &gt;&gt; https://bit.ly/NVDA-Earnings-Forecast $AAPL $TSLA $CSCO", "time": 1645130721.0, "sentiment": "Bullish"}, {"id": 437146170, "text": "$CSCO easily back to 64 plus when the dust settles with the macro.", "time": 1645130674.0, "sentiment": "Bullish"}, {"id": 437143508, "text": "These are my top four gainers this morning: $CSCO $GOLD $GME $SQ\n\nI love these stocks!", "time": 1645130340.0, "sentiment": "Bullish"}, {"id": 437141695, "text": "$SPY Today (8:34 CST), the  best performer in the $DJIA is Cisco Systems Inc. $CSCO @CQGInc @CQGThom", "time": 1645130093.0, "sentiment": ""}, {"id": 437139925, "text": "$CSCO Bloomberg showing consensus analyst 12mo tgt price of $63.18 this morning. +14% gain from here", "time": 1645129822.0, "sentiment": "Bullish"}, {"id": 437139060, "text": "Favs: $AMAT over 145, $V over 230, $CSCO over 56.50, $YNDX under 49.50, $TRIP under 26.25!!", "time": 1645129692.0, "sentiment": ""}, {"id": 437137164, "text": "$CSCO \n\nListen to JP Morgan and Barclays. Never trust Raymond James. \n\n$60\u2019s soon enough.", "time": 1645129389.0, "sentiment": "Bullish"}, {"id": 437129790, "text": "@BeRealistic they will say how everyone doesn\u2019t understand growth. Bag holders are in for a big surprise just like the early 2000s when everyone overpaid for MSFT $MU $CSCO $INTC some took over 10 years to get back to their highs and some are still waiting to get back to their highs. People need to understand they can over pay for a growth company.", "time": 1645128127.0, "sentiment": ""}, {"id": 437129337, "text": "$CSCO [Cisco Systems]: Raymond James Maintains Outperform Lowers Price Target $64 --&gt; 63 \n \n \nSign-up free for beta ver.:https://app.jarvisalerts.com \ncharts: courtesy of finviz", "time": 1645128064.0, "sentiment": ""}, {"id": 437128471, "text": "PM mOOvers \ud83d\udc40  \n \n$CSCO -Cisco Systems Q2 Adj. EPS $0.84 Beats $0.81 Estimate, Sales $12.70B Beat $12.65B Estimate. Cisco Reports $15B Buyback; Raises Qtr. Dividend From $0.37 To $0.38/Share \n \n$GLBE - Global-E Online GAAP EPS of -$0.15 beats by $0.01, revenue of $82.72M beats by $5.09M, Global-e Sees Q1 Adj. EBITDA $700K-$1.7M, Sales $74.5M-$76.5M vs $64M Estimate; FY22 Adj. EBITDA $38M-$42M, Sales $411M-$421M vs $367M Est. \n \n$AAWW - Atlas Air Worldwide Hldgs Q4 EPS $7.05 Beats $6.14 Estimate, Sales $1.20B Beat $1.11B Estimate; Reports $200M Buyback, Including $100M Accelerated Buyback \n \n$IDCC -InterDigital Q4 EPS $0.70 Beats $0.34 Estimate, Sales $111.80M Beat $101.54M Estimate. \n \n$NVTS -Needham Initiates Coverage On Navitas Semiconductor with Buy Rating, Announces Price Target of $16, Navitas and UGREEN Announce GaNFast\u2122 Global Marketing Program", "time": 1645127924.0, "sentiment": "Bullish"}, {"id": 437127090, "text": "$SPY $SOXL $NVDA $CSCO \n\nWar is good for semis and networking gears. Geez\u2026.", "time": 1645127661.0, "sentiment": "Bullish"}, {"id": 437126574, "text": "$CSCO could be in the market as early as this morning buying back shares with that $18 billion authorization. IMO the stock should see a pop to &gt;$60 soon.", "time": 1645127568.0, "sentiment": "Bullish"}, {"id": 437124769, "text": "$CSCO chuck coming up on squawk", "time": 1645127231.0, "sentiment": "Bullish"}, {"id": 437120728, "text": "$CSCO (+2.8% pre) Cisco Systems shares rise on sales, earnings that beat expectations - MW\n\nhttp://ooc.bz/l/93509", "time": 1645126415.0, "sentiment": ""}]